primitive_metadata/__init__.py
primitive_metadata/gather.py
primitive_metadata/namespaces.py
primitive_metadata/primitive_rdf.py
primitive_metadata-0.2025.1.dist-info/licenses/LICENSE
primitive_metadata-0.2025.1.dist-info/WHEEL
primitive_metadata-0.2025.1.dist-info/METADATA
primitive_metadata-0.2025.1.dist-info/RECORD
