Metadata-Version: 2.4
Name: primitive_metadata
Version: 0.2025.1
Summary: a (simple?) toolset for authoring and gathering metadata as rdf
Author-email: abram axel booth <boothaa@gmail.com>
Requires-Python: >=3.7
License-Expression: MIT
Classifier: Development Status :: 2 - Pre-Alpha
Classifier: Programming Language :: Python :: 3
Classifier: Operating System :: OS Independent
License-File: LICENSE
Project-URL: Home, https://github.com/aaxelb/primitive_metadata
Project-URL: Issues, https://github.com/aaxelb/primitive_metadata/issues
